drakaina/__init__.py
drakaina/constants.py
drakaina/contrib/__init__.py
drakaina/contrib/django/__init__.py
drakaina/contrib/django/middleware.py
drakaina/contrib/django/views.py
drakaina/contrib/jwt/__init__.py
drakaina/contrib/jwt/errors.py
drakaina/contrib/jwt/middleware.py
drakaina/contrib/jwt/types.py
drakaina/contrib/jwt/utils.py
drakaina/decorators.py
drakaina/exceptions.py
drakaina/middleware/__init__.py
drakaina/middleware/base.py
drakaina/middleware/cors.py
drakaina/middleware/exception.py
drakaina/middleware/request_wrapper.py
drakaina/registries.py
drakaina/rpc_protocols/__init__.py
drakaina/rpc_protocols/base.py
drakaina/rpc_protocols/jsonrpc20.py
drakaina/serializers.py
drakaina/types.py
drakaina/utils.py
drakaina/wsgi.py
drakaina-0.7.6.dist-info/LICENSE
drakaina-0.7.6.dist-info/METADATA
drakaina-0.7.6.dist-info/WHEEL
drakaina-0.7.6.dist-info/RECORD
