Metadata-Version: 2.1
Name: drakaina
Version: 0.7.6
Summary: Module for simple RPC service implementation
Home-page: https://gitlab.com/tau_lex/drakaina
License: Apache-2.0
Keywords: rpc,jsonrpc,openrpc
Author: Aleksey Terentyev
Author-email: terentyev.a@pm.me
Requires-Python: >=3.9,<4.0
Classifier: Development Status :: 4 - Beta
Classifier: Environment :: Web Environment
Classifier: Intended Audience :: Developers
Classifier: License :: OSI Approved :: Apache Software License
Classifier: Operating System :: OS Independent
Classifier: Programming Language :: Python :: 3
Classifier: Programming Language :: Python :: 3.9
Classifier: Programming Language :: Python :: 3.10
Classifier: Programming Language :: Python :: 3.11
Classifier: Topic :: Internet :: WWW/HTTP :: WSGI :: Application
Classifier: Topic :: Software Development :: Libraries :: Python Modules
Classifier: Topic :: System :: Networking
Provides-Extra: docs
Provides-Extra: jwt
Provides-Extra: msgpack
Provides-Extra: orjson
Provides-Extra: ujson
Requires-Dist: docstring-parser (>=0.15,<0.16) ; extra == "docs"
Requires-Dist: msgpack (>=1.0.5,<2.0.0) ; extra == "msgpack"
Requires-Dist: orjson (>=3.8.14,<4.0.0) ; extra == "orjson"
Requires-Dist: pyjwt (>=2.7.0,<3.0.0) ; extra == "jwt"
Requires-Dist: typing-extensions (>=4.6.2,<5.0.0)
Requires-Dist: ujson (>=5.7.0,<6.0.0) ; extra == "ujson"
Project-URL: Repository, https://gitlab.com/tau_lex/drakaina
